lottery_console/__init__.py
lottery_console/main.py
lottery_console-1.0.0.dist-info/LICENSE
lottery_console-1.0.0.dist-info/METADATA
lottery_console-1.0.0.dist-info/WHEEL
lottery_console-1.0.0.dist-info/entry_points.txt
lottery_console-1.0.0.dist-info/top_level.txt
lottery_console-1.0.0.dist-info/RECORD
