Metadata-Version: 2.1
Name: lottery_console
Version: 1.0.0
Summary: very helpful lottery
Home-page: https://github.com/VadimTrubay/lottery_console
Author: TrubayVadim
Author-email: vadnetvadnet@ukr.net
License: MIT
License-File: LICENSE
Requires-Dist: colorama
